{"LSTc": "RES\n1b:x-dglc-HEX-1:5\n2b:b-dgal-HEX-1:5\n3b:b-dglc-HEX-1:5\n4s:n-acetyl\n5b:b-dgal-HEX-1:5\n6b:a-dgro-dgal-NON-2:6|1:a|2:keto|3:d\n7s:n-acetyl\nLIN\n1:1o(4+1)2d\n2:2o(3+1)3d\n3:3d(2+1)4n\n4:3o(4+1)5d\n5:5o(6+2)6d\n6:6d(5+1)7n\n", "LNT": "RES\n1b:x-dglc-HEX-1:5\n2b:b-dgal-HEX-1:5\n3b:b-dglc-HEX-1:5\n4s:n-acetyl\n5b:b-dgal-HEX-1:5\nLIN\n1:1o(4+1)2d\n2:2o(3+1)3d\n3:3d(2+1)4n\n4:3o(3+1)5d\n", "LSTb": "RES\n1b:x-dglc-HEX-1:5\n2b:b-dgal-HEX-1:5\n3b:b-dglc-HEX-1:5\n4s:n-acetyl\n5b:b-dgal-HEX-1:5\n6b:a-dgro-dgal-NON-2:6|1:a|2:keto|3:d\n7s:n-acetyl\nLIN\n1:1o(4+1)2d\n2:2o(3+1)3d\n3:3d(2+1)4n\n4:3o(3+1)5d\n5:3o(6+2)6d\n6:6d(5+1)7n\n", "FDSLNH": "RES\n1b:x-dglc-HEX-1:5\n2b:b-dgal-HEX-1:5\n3b:b-dglc-HEX-1:5\n4s:n-acetyl\n5b:a-lgal-HEX-1:5|6:d\n6b:b-dgal-HEX-1:5\n7b:a-dgro-dgal-NON-2:6|1:a|2:keto|3:d\n8s:n-acetyl\n9b:b-dglc-HEX-1:5\n10s:n-acetyl\n11b:b-dgal-HEX-1:5\n12b:a-dgro-dgal-NON-2:6|1:a|2:keto|3:d\n13s:n-acetyl\nLIN\n1:1o(4+1)2d\n2:2o(3+1)3d\n3:3d(2+1)4n\n4:3o(3+1)5d\n5:3o(4+1)6d\n6:6o(6+2)7d\n7:7d(5+1)8n\n8:2o(6+1)9d\n9:9d(2+1)10n\n10:9o(4+1)11d\n11:11o(6+2)12d\n12:12d(5+1)13n\n", "LNFP III": "RES\n1b:x-dglc-HEX-1:5\n2b:b-dgal-HEX-1:5\n3b:b-dglc-HEX-1:5\n4s:n-acetyl\n5b:a-lgal-HEX-1:5|6:d\n6b:b-dgal-HEX-1:5\nLIN\n1:1o(4+1)2d\n2:2o(3+1)3d\n3:3d(2+1)4n\n4:3o(3+1)5d\n5:3o(4+1)6d\n", "2'FL": "RES\n1b:x-dglc-HEX-1:5\n2b:b-dgal-HEX-1:5\n3b:a-lgal-HEX-1:5|6:d\nLIN\n1:1o(4+1)2d\n2:2o(2+1)3d\n", "LNFP I": "RES\n1b:x-dglc-HEX-1:5\n2b:b-dgal-HEX-1:5\n3b:b-dglc-HEX-1:5\n4s:n-acetyl\n5b:b-dgal-HEX-1:5\n6b:a-lgal-HEX-1:5|6:d\nLIN\n1:1o(4+1)2d\n2:2o(3+1)3d\n3:3d(2+1)4n\n4:3o(3+1)5d\n5:5o(2+1)6d\n", "LNFP II": "RES\n1b:x-dglc-HEX-1:5\n2b:b-dgal-HEX-1:5\n3b:b-dglc-HEX-1:5\n4s:n-acetyl\n5b:b-dgal-HEX-1:5\n6b:a-lgal-HEX-1:5|6:d\nLIN\n1:1o(4+1)2d\n2:2o(3+1)3d\n3:3d(2+1)4n\n4:3o(3+1)5d\n5:3o(4+1)6d\n", "LNnT": "RES\n1b:x-dglc-HEX-1:5\n2b:b-dgal-HEX-1:5\n3b:b-dglc-HEX-1:5\n4s:n-acetyl\n5b:b-dgal-HEX-1:5\nLIN\n1:1o(4+1)2d\n2:2o(3+1)3d\n3:3d(2+1)4n\n4:3o(4+1)5d\n", "3FL": "RES\n1b:x-dglc-HEX-1:5\n2b:a-lgal-HEX-1:5|6:d\n3b:b-dgal-HEX-1:5\nLIN\n1:1o(3+1)2d\n2:1o(4+1)3d\n", "DFLNT": "RES\n1b:x-dglc-HEX-1:5\n2b:a-lgal-HEX-1:5|6:d\n3b:b-dgal-HEX-1:5\n4b:b-dglc-HEX-1:5\n5s:n-acetyl\n6b:b-dgal-HEX-1:5\n7b:a-lgal-HEX-1:5|6:d\nLIN\n1:1o(3+1)2d\n2:1o(4+1)3d\n3:3o(3+1)4d\n4:4d(2+1)5n\n5:4o(3+1)6d\n6:4o(4+1)7d\n", "DSLNH": "RES\n1b:x-dglc-HEX-1:5\n2b:b-dgal-HEX-1:5\n3b:b-dglc-HEX-1:5\n4s:n-acetyl\n5b:b-dgal-HEX-1:5\n6b:a-dgro-dgal-NON-2:6|1:a|2:keto|3:d\n7s:n-acetyl\n8b:a-dgro-dgal-NON-2:6|1:a|2:keto|3:d\n9s:n-acetyl\n10b:b-dglc-HEX-1:5\n11s:n-acetyl\n12b:b-dgal-HEX-1:5\nLIN\n1:1o(4+1)2d\n2:2o(3+1)3d\n3:3d(2+1)4n\n4:3o(3+1)5d\n5:5o(3+2)6d\n6:6d(5+1)7n\n7:3o(6+2)8d\n8:8d(5+1)9n\n9:2o(6+1)10d\n10:10d(2+1)11n\n11:10o(4+1)12d\n", "DFLNH": "RES\n1b:x-dglc-HEX-1:5\n2b:b-dgal-HEX-1:5\n3b:b-dglc-HEX-1:5\n4s:n-acetyl\n5b:a-lgal-HEX-1:5|6:d\n6b:b-dgal-HEX-1:5\n7b:b-dglc-HEX-1:5\n8s:n-acetyl\n9b:a-lgal-HEX-1:5|6:d\n10b:b-dgal-HEX-1:5\nLIN\n1:1o(4+1)2d\n2:2o(3+1)3d\n3:3d(2+1)4n\n4:3o(3+1)5d\n5:3o(4+1)6d\n6:2o(6+1)7d\n7:7d(2+1)8n\n8:7o(3+1)9d\n9:7o(4+1)10d\n", "FLNH": "RES\n1b:x-dglc-HEX-1:5\n2b:b-dgal-HEX-1:5\n3b:b-dglc-HEX-1:5\n4s:n-acetyl\n5b:b-dgal-HEX-1:5\n6b:a-lgal-HEX-1:5|6:d\n7b:b-dglc-HEX-1:5\n8s:n-acetyl\n9b:b-dgal-HEX-1:5\nLIN\n1:1o(4+1)2d\n2:2o(3+1)3d\n3:3d(2+1)4n\n4:3o(3+1)5d\n5:5o(2+1)6d\n6:2o(6+1)7d\n7:7d(2+1)8n\n8:7o(4+1)9d\n", "3'SL": "RES\n1b:b-dglc-HEX-1:5\n2b:b-dgal-HEX-1:5\n3b:a-dgro-dgal-NON-2:6|1:a|2:keto|3:d\n4s:n-acetyl\nLIN\n1:1o(4+1)2d\n2:2o(3+2)3d\n3:3d(5+1)4n\n", "DSLNT": "RES\n1b:x-dglc-HEX-1:5\n2b:b-dgal-HEX-1:5\n3b:b-dglc-HEX-1:5\n4s:n-acetyl\n5b:b-dgal-HEX-1:5\n6b:a-dgro-dgal-NON-2:6|1:a|2:keto|3:d\n7s:n-acetyl\n8b:a-dgro-dgal-NON-2:6|1:a|2:keto|3:d\n9s:n-acetyl\nLIN\n1:1o(4+1)2d\n2:2o(3+1)3d\n3:3d(2+1)4n\n4:3o(3+1)5d\n5:5o(3+2)6d\n6:6d(5+1)7n\n7:3o(6+2)8d\n8:8d(5+1)9n\n"}